aiotelegrambot/__init__.py
aiotelegrambot/bot.py
aiotelegrambot/client.py
aiotelegrambot/errors.py
aiotelegrambot/handler.py
aiotelegrambot/message.py
aiotelegrambot/middleware.py
aiotelegrambot/rules.py
aiotelegrambot/types.py
aio_telegram_bot-1.0.0.dist-info/LICENSE
aio_telegram_bot-1.0.0.dist-info/METADATA
aio_telegram_bot-1.0.0.dist-info/WHEEL
aio_telegram_bot-1.0.0.dist-info/top_level.txt
aio_telegram_bot-1.0.0.dist-info/RECORD
