Metadata-Version: 2.1
Name: aio-telegram-bot
Version: 1.0.0
Summary: An asynchronous framework for building your own Telegram Bot
Home-page: https://github.com/v-v-vishnevskiy/aio-telegram-bot
Author: Valery Vishnevskiy
Author-email: v.v.vishnevskiy@gmail.com
License: MIT
Project-URL: CI: Travis, https://travis-ci.org/v-v-vishnevskiy/aio-telegram-bot
Project-URL: Coverage: codecov, https://codecov.io/gh/v-v-vishnevskiy/aio-telegram-bot
Project-URL: GitHub: repo, https://github.com/v-v-vishnevskiy/aio-telegram-bot
Keywords: aio,async,asyncio,telegram,bot
Platform: UNKNOWN
Classifier: Development Status :: 4 - Beta
Classifier: Environment :: Console
Classifier: Environment :: Web Environment
Classifier: Framework :: AsyncIO
Classifier: License :: OSI Approved :: MIT License
Classifier: Intended Audience :: Developers
Classifier: Operating System :: POSIX
Classifier: Operating System :: MacOS :: MacOS X
Classifier: Operating System :: Microsoft :: Windows
Classifier: Programming Language :: Python :: 3 :: Only
Classifier: Programming Language :: Python :: 3.5
Classifier: Programming Language :: Python :: 3.6
Classifier: Programming Language :: Python :: 3.7
Classifier: Programming Language :: Python :: Implementation :: PyPy
Classifier: Topic :: Communications :: Chat
Classifier: Topic :: Internet :: WWW/HTTP
Classifier: Topic :: Software Development :: Libraries :: Python Modules
Provides: aiotelegrambot
Requires-Python: >=3.5.3
Requires-Dist: aiohttp (==3.5.4)
Requires-Dist: aiojobs (==0.2.2)
